TurnTouch-0.4.3.dist-info/METADATA
TurnTouch-0.4.3.dist-info/RECORD
TurnTouch-0.4.3.dist-info/WHEEL
TurnTouch-0.4.3.dist-info/top_level.txt
turntouch/__init__.py
turntouch/scan.py
turntouch/turntouch.py
