Metadata-Version: 2.1
Name: TurnTouch
Version: 0.4.3
Summary: Python library for the Turn Touch smart home remote
Home-page: https://github.com/antsar/python-turntouch
Author: Anton Sarukhanov
Author-email: code@ant.sr
License: MIT
Platform: UNKNOWN
Classifier: Development Status :: 4 - Beta
Classifier: Intended Audience :: Developers
Classifier: Environment :: Console
Classifier: License :: OSI Approved :: MIT License
Classifier: Natural Language :: English
Classifier: Programming Language :: Python :: 3.5
Classifier: Topic :: Home Automation
Requires-Dist: bluepy (==1.1.4)
